fjutils/__init__.py
fjutils/checkpointing.py
fjutils/easylm.py
fjutils/flash_attention.py
fjutils/load.py
fjutils/loss_funcs.py
fjutils/optimizers.py
fjutils/tracker.py
fjutils/utils.py
FJUtils-0.0.21.dist-info/LICENSE
FJUtils-0.0.21.dist-info/METADATA
FJUtils-0.0.21.dist-info/WHEEL
FJUtils-0.0.21.dist-info/top_level.txt
FJUtils-0.0.21.dist-info/RECORD
