Metadata-Version: 2.1
Name: FJUtils
Version: 0.0.21
Home-page: https://github.com/erfanzar/
Author: Erfan Zare Chavoshi
Author-email: erfanzare82@yahoo.com
License: Apache License 2.0
Classifier: Programming Language :: Python :: 3
Classifier: License :: OSI Approved :: MIT License
Classifier: Operating System :: OS Independent
Classifier: Programming Language :: Python :: 3
Classifier: Programming Language :: Python :: 3.7
Classifier: Programming Language :: Python :: 3.8
Classifier: Programming Language :: Python :: 3.9
Classifier: Programming Language :: Python :: 3.10
Classifier: Programming Language :: Python :: 3.11
Requires-Python: >=3.7
License-File: LICENSE
Requires-Dist: numpy
Requires-Dist: jax >=0.4.10
Requires-Dist: transformers >=4.34.0
Requires-Dist: typing ~=3.7.4.3
Requires-Dist: flax >=0.7.1
Requires-Dist: optax >=0.1.7
Requires-Dist: einops >=0.6.1
Requires-Dist: msgpack >=1.0.5
Requires-Dist: ml-collections
